iplotx/__init__.py
iplotx/artists.py
iplotx/label.py
iplotx/plotting.py
iplotx/typing.py
iplotx/version.py
iplotx/vertex.py
iplotx/art3d/vertex.py
iplotx/art3d/edge/__init__.py
iplotx/art3d/edge/arrow.py
iplotx/art3d/edge/geometry.py
iplotx/edge/__init__.py
iplotx/edge/arrow.py
iplotx/edge/geometry.py
iplotx/edge/leaf.py
iplotx/edge/ports.py
iplotx/ingest/__init__.py
iplotx/ingest/heuristics.py
iplotx/ingest/typing.py
iplotx/ingest/providers/network/graph_tool.py
iplotx/ingest/providers/network/igraph.py
iplotx/ingest/providers/network/networkx.py
iplotx/ingest/providers/network/simple.py
iplotx/ingest/providers/tree/biopython.py
iplotx/ingest/providers/tree/cogent3.py
iplotx/ingest/providers/tree/dendropy.py
iplotx/ingest/providers/tree/ete4.py
iplotx/ingest/providers/tree/simple.py
iplotx/ingest/providers/tree/skbio.py
iplotx/layout/__init__.py
iplotx/layout/tree/__init__.py
iplotx/layout/tree/rooted.py
iplotx/layout/tree/unrooted.py
iplotx/network/__init__.py
iplotx/network/groups.py
iplotx/style/__init__.py
iplotx/style/leaf_info.py
iplotx/style/library.py
iplotx/tree/__init__.py
iplotx/tree/cascades.py
iplotx/tree/scalebar.py
iplotx/utils/geometry.py
iplotx/utils/internal.py
iplotx/utils/matplotlib.py
iplotx/utils/style.py
iplotx-1.5.1.dist-info/METADATA
iplotx-1.5.1.dist-info/WHEEL
iplotx-1.5.1.dist-info/RECORD
