Metadata-Version: 2.4
Name: iplotx
Version: 1.5.1
Summary: Plot networkx from igraph and networkx.
Project-URL: Homepage, https://github.com/fabilab/iplotx
Project-URL: Documentation, https://readthedocs.org/iplotx
Project-URL: Repository, https://github.com/fabilab/iplotx.git
Project-URL: Bug Tracker, https://github.com/fabilab/iplotx/issues
Project-URL: Changelog, https://github.com/fabilab/iplotx/blob/main/CHANGELOG.md
Author-email: Fabio Zanini <fabio.zanini@unsw.edu.au>
Maintainer-email: Fabio Zanini <fabio.zanini@unsw.edu.au>
License: MIT
Keywords: graph,network,phylogeny,plotting,tree,visualisation
Classifier: Development Status :: 5 - Production/Stable
Classifier: Framework :: Matplotlib
Classifier: Intended Audience :: Developers
Classifier: Intended Audience :: Education
Classifier: Intended Audience :: Science/Research
Classifier: License :: OSI Approved :: MIT License
Classifier: Natural Language :: English
Classifier: Operating System :: OS Independent
Classifier: Programming Language :: Python :: 3
Classifier: Programming Language :: Python :: 3.11
Classifier: Programming Language :: Python :: 3.12
Classifier: Programming Language :: Python :: 3.13
Classifier: Topic :: Scientific/Engineering :: Visualization
Classifier: Topic :: System :: Networking
Classifier: Typing :: Typed
Requires-Python: >=3.10
Requires-Dist: matplotlib>=3.10.0
Requires-Dist: numpy>=2.0.0
Requires-Dist: pandas>=2.0.0
Provides-Extra: igraph
Requires-Dist: igraph>=0.11.0; extra == 'igraph'
Provides-Extra: networkx
Requires-Dist: networkx>=2.0.0; extra == 'networkx'
